j2fa
