Metadata-Version: 2.1
Name: django-j2fa
Version: 3.8.12
Summary: 2-Factor Authentication for Django projects
Home-page: 
Author: Jani Kajala
Author-email: kajala@gmail.com
License: MIT licence, see LICENCE.txt
License-File: LICENSE.txt
Requires-Dist: Django>=2.1.7
Requires-Dist: django-ipware>=3.0.0
Requires-Dist: requests>=2.19.1
